{
  "total_pitches": null,
  "pitch_types": [
    "Fastball",
    "Other",
    "Slider"
  ],
  "pitch_mix_pct": null,
  "weighted_avg_velocity_mph": 79.95,
  "max_velocity_mph": 83.96,
  "weighted_avg_spin_rpm": 2073.07,
  "max_spin_rpm": 2168.79,
  "weighted_avg_ivb_in": 5.18,
  "weighted_avg_hb_in": -3.23,
  "weighted_avg_extension_ft": 6.91,
  "weighted_avg_rel_height_ft": 5.38,
  "weighted_avg_rel_side_ft": 1.91,
  "weighted_avg_spin_axis_2d": 147.67,
  "weighted_avg_spin_axis_3d": null,
  "weighted_avg_gyro": null,
  "per_type": [
    {
      "pitch_type": "Fastball",
      "count": null,
      "avg_velocity_mph": 83.96,
      "avg_spin_rpm": 2168.79,
      "avg_ivb_in": 11.57,
      "avg_hb_in": 0.27,
      "avg_extension_ft": 7.22,
      "avg_rel_height_ft": 5.38,
      "avg_rel_side_ft": 1.78,
      "avg_spin_axis_2d": 181.0,
      "avg_spin_axis_3d": null,
      "avg_gyro": null,
      "max_velocity_mph": 83.96,
      "max_spin_rpm": 2168.79
    },
    {
      "pitch_type": "Slider",
      "count": null,
      "avg_velocity_mph": 77.03,
      "avg_spin_rpm": 2127.06,
      "avg_ivb_in": 0.05,
      "avg_hb_in": -9.96,
      "avg_extension_ft": 6.7,
      "avg_rel_height_ft": 5.26,
      "avg_rel_side_ft": 1.9,
      "avg_spin_axis_2d": 93.0,
      "avg_spin_axis_3d": null,
      "avg_gyro": null,
      "max_velocity_mph": 77.03,
      "max_spin_rpm": 2127.06
    },
    {
      "pitch_type": "Other",
      "count": null,
      "avg_velocity_mph": 78.87,
      "avg_spin_rpm": 1923.35,
      "avg_ivb_in": 3.91,
      "avg_hb_in": -0.01,
      "avg_extension_ft": 6.8,
      "avg_rel_height_ft": 5.5,
      "avg_rel_side_ft": 2.05,
      "avg_spin_axis_2d": 169.0,
      "avg_spin_axis_3d": null,
      "avg_gyro": null,
      "max_velocity_mph": 78.87,
      "max_spin_rpm": 1923.35
    }
  ]
}
